wr_profiles/__init__.py
wr_profiles/envvar_profile.py
wr_profiles-4.2.1.dist-info/METADATA
wr_profiles-4.2.1.dist-info/RECORD
wr_profiles-4.2.1.dist-info/WHEEL
wr_profiles-4.2.1.dist-info/top_level.txt
